{
  "age_years": 46.92,
  "dataset": "main",
  "date": "1999-09-08",
  "expression_flags": {
    "jaw_excluded": false,
    "neutralized": false,
    "smile_excluded": false
  },
  "face_bbox": [
    37,
    14,
    185,
    161
  ],
  "face_mask_path": "/Users/victorkhudyakov/deeputin/data/storage/main/1999_09_08/face_mask.png",
  "image_size": [
    1200,
    1200
  ],
  "photo_id": "1999_09_08",
  "pose": {
    "age_years": 46.92,
    "bucket": "left_threequarter_light",
    "confidence": 0.8,
    "date": "1999-09-08",
    "photo_id": "1999_09_08",
    "pitch": 17.36114501953125,
    "pose_source": "3ddfa_v3",
    "roll": -4.944775581359863,
    "yaw": -23.1154727935791
  },
  "quality": {
    "blur_value": 11.921600672974055,
    "face_min_dim": 0,
    "is_jpeg_blocky": true,
    "is_motion_blurred": false,
    "is_over_smoothed": false,
    "jpeg_blockiness": 1.5109744548797608,
    "noise_level": 0.33961042761802673,
    "overall_quality": 0.3054341739486416,
    "ppIOD": 0.0,
    "q_laplacian_var": 0.0,
    "q_tenengrad": 0.0,
    "q_valid_patches": 0,
    "sharpness_score": 0.011921600672974054
  },
  "readiness": {
    "geometry": "available",
    "texture": "available"
  },
  "reconstruction_path": "/Users/victorkhudyakov/deeputin/data/storage/main/1999_09_08/reconstruction.pkl",
  "source_path": "/Users/victorkhudyakov/deeputin/data/photo/all/1999_09_08.jpg"
}